{
  "$schema": "https://biomejs.dev/schemas/2.5.3/schema.json",
  "files": {
    "includes": [
      "apps/**/src/**",
      "packages/**/src/**",
      "e2e/**",
      "!**/dist",
      "!**/node_modules"
    ]
  },
  "formatter": {
    "enabled": false
  },
  "linter": {
    "enabled": true,
    "rules": {
      "recommended": true,
      "style": {
        "noNonNullAssertion": "off",
        "noParameterAssign": "off",
        "useTemplate": "off",
        "noDescendingSpecificity": "warn"
      },
      "suspicious": {
        "noExplicitAny": "off",
        "noAssignInExpressions": "off",
        "noConfusingVoidType": "off",
        "noControlCharactersInRegex": "off",
        "noArrayIndexKey": "warn"
      },
      "complexity": {
        "noForEach": "off",
        "noImportantStyles": "off"
      },
      "correctness": {
        "useExhaustiveDependencies": "off"
      },
      "a11y": {
        "useKeyWithClickEvents": "off",
        "noStaticElementInteractions": "off",
        "useSemanticElements": "off",
        "noAutofocus": "off",
        "noLabelWithoutControl": "off"
      }
    }
  },
  "assist": {
    "enabled": false
  }
}